[
  {
    "word": "«Да",
    "start": 0.0,
    "end": 0.253
  },
  {
    "word": "пизды",
    "start": 0.253,
    "end": 0.598
  },
  {
    "word": "что",
    "start": 0.828,
    "end": 0.828
  },
  {
    "word": "она",
    "start": 0.828,
    "end": 1.081
  },
  {
    "word": "10",
    "start": 1.081,
    "end": 1.334
  },
  {
    "word": "out",
    "start": 1.334,
    "end": 1.518
  },
  {
    "word": "of",
    "start": 1.518,
    "end": 1.725
  },
  {
    "word": "10",
    "start": 1.725,
    "end": 1.955
  },
  {
    "word": "»",
    "start": 1.955,
    "end": 2.599
  },
  {
    "word": "Давайте",
    "start": 2.599,
    "end": 2.668
  },
  {
    "word": "лучше",
    "start": 2.668,
    "end": 3.059
  },
  {
    "word": "разберёмся",
    "start": 3.059,
    "end": 3.91
  },
  {
    "word": "Джон",
    "start": 4.554,
    "end": 4.807
  },
  {
    "word": "Готман",
    "start": 4.807,
    "end": 5.152
  },
  {
    "word": "в",
    "start": 5.152,
    "end": 5.313
  },
  {
    "word": "книге",
    "start": 5.313,
    "end": 5.566
  },
  {
    "word": "«Seven",
    "start": 5.566,
    "end": 6.026
  },
  {
    "word": "Principles",
    "start": 6.026,
    "end": 6.44
  },
  {
    "word": "of",
    "start": 6.44,
    "end": 6.739
  },
  {
    "word": "Marriage»",
    "start": 6.739,
    "end": 7.222
  },
  {
    "word": "пишет",
    "start": 7.222,
    "end": 7.613
  },
  {
    "word": "«Самая",
    "start": 7.728,
    "end": 8.349
  },
  {
    "word": "частая",
    "start": 8.349,
    "end": 8.717
  },
  {
    "word": "ошибка",
    "start": 8.717,
    "end": 9.108
  },
  {
    "word": "пар",
    "start": 9.108,
    "end": 9.384
  },
  {
    "word": "—",
    "start": 9.384,
    "end": 9.982
  },
  {
    "word": "ожидать",
    "start": 9.982,
    "end": 10.028
  },
  {
    "word": "что",
    "start": 10.189,
    "end": 10.212
  },
  {
    "word": "партнёр",
    "start": 10.212,
    "end": 10.534
  },
  {
    "word": "прочитает",
    "start": 10.534,
    "end": 11.109
  },
  {
    "word": "мысли",
    "start": 11.109,
    "end": 11.477
  },
  {
    "word": "Ты",
    "start": 12.006,
    "end": 12.19
  },
  {
    "word": "думаешь",
    "start": 12.19,
    "end": 12.558
  },
  {
    "word": "ну",
    "start": 12.719,
    "end": 13.248
  },
  {
    "word": "это",
    "start": 13.248,
    "end": 13.432
  },
  {
    "word": "же",
    "start": 13.432,
    "end": 13.754
  },
  {
    "word": "очевидно",
    "start": 13.754,
    "end": 14.283
  },
  {
    "word": "он",
    "start": 14.605,
    "end": 14.743
  },
  {
    "word": "должен",
    "start": 14.743,
    "end": 15.042
  },
  {
    "word": "понимать",
    "start": 15.042,
    "end": 15.571
  },
  {
    "word": "Если",
    "start": 16.123,
    "end": 16.33
  },
  {
    "word": "любит",
    "start": 16.33,
    "end": 16.721
  },
  {
    "word": "догадается",
    "start": 16.951,
    "end": 17.526
  },
  {
    "word": "Но",
    "start": 17.986,
    "end": 18.193
  },
  {
    "word": "он",
    "start": 18.193,
    "end": 18.423
  },
  {
    "word": "не",
    "start": 18.423,
    "end": 18.607
  },
  {
    "word": "догадается",
    "start": 18.607,
    "end": 19.251
  },
  {
    "word": "потому",
    "start": 19.642,
    "end": 19.826
  },
  {
    "word": "что",
    "start": 19.826,
    "end": 20.01
  },
  {
    "word": "у",
    "start": 20.01,
    "end": 20.263
  },
  {
    "word": "него",
    "start": 20.263,
    "end": 20.263
  },
  {
    "word": "другая",
    "start": 20.263,
    "end": 20.7
  },
  {
    "word": "голова",
    "start": 20.7,
    "end": 21.022
  },
  {
    "word": "другой",
    "start": 21.643,
    "end": 21.85
  },
  {
    "word": "опыт",
    "start": 21.85,
    "end": 22.264
  },
  {
    "word": "другие",
    "start": 23.023,
    "end": 23.023
  },
  {
    "word": "ассоциации",
    "start": 23.023,
    "end": 23.759
  },
  {
    "word": "и",
    "start": 24.104,
    "end": 24.288
  },
  {
    "word": "это",
    "start": 24.288,
    "end": 24.495
  },
  {
    "word": "нормально",
    "start": 24.495,
    "end": 24.932
  },
  {
    "word": "Решение",
    "start": 25.645,
    "end": 25.921
  },
  {
    "word": "—",
    "start": 25.921,
    "end": 26.473
  },
  {
    "word": "не",
    "start": 26.473,
    "end": 26.473
  },
  {
    "word": "ждать",
    "start": 26.473,
    "end": 26.772
  },
  {
    "word": "телепатии",
    "start": 26.772,
    "end": 27.347
  },
  {
    "word": "а",
    "start": 27.439,
    "end": 27.738
  },
  {
    "word": "показывать",
    "start": 27.738,
    "end": 28.152
  },
  {
    "word": "конкретно",
    "start": 28.152,
    "end": 28.75
  },
  {
    "word": "что",
    "start": 28.842,
    "end": 28.911
  },
  {
    "word": "тебе",
    "start": 28.911,
    "end": 29.118
  },
  {
    "word": "важно",
    "start": 29.118,
    "end": 29.463
  },
  {
    "word": "В",
    "start": 29.854,
    "end": 30.061
  },
  {
    "word": "Bloom",
    "start": 30.061,
    "end": 30.337
  },
  {
    "word": "мы",
    "start": 30.337,
    "end": 30.567
  },
  {
    "word": "собрали",
    "start": 30.567,
    "end": 30.889
  },
  {
    "word": "готовые",
    "start": 30.889,
    "end": 31.418
  },
  {
    "word": "идеи",
    "start": 31.418,
    "end": 31.901
  },
  {
    "word": "которые",
    "start": 31.901,
    "end": 32.476
  },
  {
    "word": "говорят",
    "start": 32.476,
    "end": 32.89
  },
  {
    "word": "«я",
    "start": 32.89,
    "end": 33.281
  },
  {
    "word": "думаю",
    "start": 33.281,
    "end": 33.626
  },
  {
    "word": "о",
    "start": 33.626,
    "end": 33.856
  },
  {
    "word": "тебе»",
    "start": 33.856,
    "end": 34.569
  },
  {
    "word": "без",
    "start": 34.569,
    "end": 34.569
  },
  {
    "word": "слов",
    "start": 34.569,
    "end": 34.891
  },
  {
    "word": "Ссылка",
    "start": 35.604,
    "end": 35.742
  },
  {
    "word": "в",
    "start": 35.742,
    "end": 35.834
  },
  {
    "word": "шапке",
    "start": 35.834,
    "end": 36.133
  },
  {
    "word": "профиля",
    "start": 36.133,
    "end": 36.432
  }
]